[
    {
        "symbol": "mes",
        "direction": "long",
        "entry": 7839.75,
        "exit": 7900.0,
        "pnl": 60.25,
        "result": "Win"
    },
    {
        "symbol": "mnq",
        "direction": "short",
        "entry": 8740.5,
        "exit": 8720.5,
        "pnl": 20.0,
        "result": "Win"
    },
    {
        "symbol": "mnq",
        "direction": "long",
        "entry": 7839.0,
        "exit": 7703.65,
        "pnl": -135.35000000000036,
        "result": "Loss"
    },
    {
        "symbol": "eurusd",
        "direction": "short",
        "entry": 5000.0,
        "exit": 4000.0,
        "pnl": 1000.0,
        "result": "Win"
    }
]